[
    {
        "url" : "./img/empresas/Acciona.webp",
        "company": "acciona",
        "name": "acciona"
    } ,
    {
        "url" : "./img/empresas/Astrazeca.webp",
        "company": "astrazeca",
        "name":"astrazeca"
    },
    {
        "url" : "./img/empresas/Atresmedia.webp",
        "company": "atresmedia",
        "name":"atresmedia"
    },
    {
        "url" : "./img/empresas/Barcelona.webp",
        "company": "barcelona",
        "name":"barcelona"
    },
    {
        "url" : "./img/empresas/CaixaBanc.webp",
        "company": "caixabanc",
        "name":"caixabanc"
    },
    {
        "url" : "./img/empresas/Cosmopolitan.webp",
        "company": "cosmopolitan",
        "name":"cosmopolitan"
    },
    {
        "url" : "./img/empresas/Dell.webp",
        "company": "dell",
        "name":"dell"
    },
    {
        "url" : "./img/empresas/Esquire.webp",
        "company": "esquire",
        "name":"esquire"
    },
    {
        "url" : "./img/empresas/Fore.webp",
        "company": "fore",
        "name":"fore"
    },
    {
        "url" : "./img/empresas/Google.webp",
        "company": "google",
        "name":"google"
    },
    {
        "url" : "./img/empresas/Nissan.webp",
        "company": "nissan",
        "name":"nissan"
    },
    {
        "url" : "./img/empresas/Scalpers.webp",
        "company": "scalpers",
        "name":"scalpers"
    },
    {
        "url" : "./img/empresas/Servi.webp",
        "company": "servi",
        "name":"servi"
    },
    {
        "url" : "./img/empresas/TikTok.webp",
        "company": "tiktok",
        "name":"tiktok"
    }
    
]
